fit_growth_mcp_tools_idc/__init__.py
fit_growth_mcp_tools_idc/__main__.py
fit_growth_mcp_tools_idc-0.1.0.dist-info/WHEEL
fit_growth_mcp_tools_idc-0.1.0.dist-info/entry_points.txt
fit_growth_mcp_tools_idc-0.1.0.dist-info/METADATA
fit_growth_mcp_tools_idc-0.1.0.dist-info/RECORD
