Metadata-Version: 2.3
Name: fit-growth-mcp-tools-idc
Version: 0.1.0
Summary: Add your description here
Requires-Dist: python-dotenv>=1.0.0
Requires-Dist: mcp[cli]>=1.12.4
Requires-Dist: requests>=2.31.0
Requires-Dist: chardet>=5.0.0
Requires-Python: >=3.12
